LICENSE.md
MANIFEST.in
README.md
setup.cfg
setup.py
src/__init__.py
src/pkg_inspect/__init__.py
src/pkg_inspect.egg-info/PKG-INFO
src/pkg_inspect.egg-info/SOURCES.txt
src/pkg_inspect.egg-info/dependency_links.txt
src/pkg_inspect.egg-info/entry_points.txt
src/pkg_inspect.egg-info/top_level.txt
src/pkg_inspect/pkg_functions/__init__.py
src/pkg_inspect/pkg_functions/functions.py
src/pkg_inspect/pkg_modules/__init__.py
src/pkg_inspect/pkg_modules/pkg_inspect.py
src/pkg_inspect/pkg_modules/pkg_metrics.py
src/pkg_inspect/pkg_modules/pkg_versions.py
src/pkg_inspect/pkg_utils/__init__.py
src/pkg_inspect/pkg_utils/cli.py
src/pkg_inspect/pkg_utils/exception.py
src/pkg_inspect/pkg_utils/metadata.py
src/pkg_inspect/pkg_utils/util_types.py
src/pkg_inspect/pkg_utils/utils.py
tests/__init__.py
tests/test_pkg_inspect.py