Metadata-Version: 2.1
Name: pkg-inspect
Version: 0.1.8
Summary: A package for inspecting Python packages and their versions.
Home-page: https://github.com/yousefabuz17/PkgInspect
Download-URL: https://github.com/yousefabuz17/PkgInspect.git
Author: Yousef Abuzahrieh
Author-email: yousefzahrieh17@gmail.com
License: Apache Software License
Platform: Windows
Platform: Linux
Platform: MacOS
Classifier: Development Status :: 4 - Beta
Classifier: Intended Audience :: Developers
Classifier: License :: OSI Approved :: Apache Software License
Classifier: Operating System :: OS Independent
Classifier: Programming Language :: Python :: 3
Classifier: Programming Language :: Python :: 3 :: Only
Classifier: Topic :: Utilities
License-File: LICENSE.md
